alfred/__init__.py
alfred/__main__.py
alfred_installer-0.1.2.dist-info/LICENSE
alfred_installer-0.1.2.dist-info/METADATA
alfred_installer-0.1.2.dist-info/WHEEL
alfred_installer-0.1.2.dist-info/entry_points.txt
alfred_installer-0.1.2.dist-info/top_level.txt
alfred_installer-0.1.2.dist-info/RECORD
