Metadata-Version: 2.1
Name: alfred-installer
Version: 0.1.2
Summary: A script to install all your favourite applications and perform the most common tasks in Debian, Ubuntu and derivatives
Home-page: https://github.com/derkomai/alfred
Author: David Vilela
Author-email: dvilelaf@gmail.com
License: UNKNOWN
Platform: UNKNOWN
Classifier: Programming Language :: Python :: 3
Classifier: License :: OSI Approved :: GNU General Public License v3 (GPLv3)
Classifier: Operating System :: POSIX :: Linux
